Metadata-Version: 2.1
Name: ellipsefitting
Version: 1.0
Summary: Least squares fitting of Ellipses
Home-page: https://github.com/ehtec/least-squares-ellipse-fitting
Author: Elias Hohl
Author-email: elias.hohl@ehtec.co
License: MIT
Platform: UNKNOWN
